{
    "directed": false,
    "multigraph": false,
    "graph": {},
    "nodes": [
        {
            "name": 0,
            "voltage_level": "medium voltage",
            "color": "rgb(31, 119, 180)",
            "active_power": 0.0,
            "reactive_power": 0.0,
            "id": 0
        },
        {
            "name": 1,
            "voltage_level": "medium voltage",
            "color": "rgb(31, 119, 180)",
            "active_power": 0.0,
            "reactive_power": 0.0,
            "id": 1
        },
        {
            "name": 2,
            "voltage_level": "medium voltage",
            "color": "rgb(31, 119, 180)",
            "active_power": 0.0,
            "reactive_power": 0.0,
            "id": 2
        },
        {
            "name": 3,
            "voltage_level": "medium voltage",
            "color": "rgb(31, 119, 180)",
            "active_power": 0.0,
            "reactive_power": 0.0,
            "id": 3
        },
        {
            "name": 4,
            "voltage_level": "medium voltage",
            "color": "rgb(31, 119, 180)",
            "active_power": 0.0,
            "reactive_power": 0.0,
            "id": 4
        },
        {
            "name": 5,
            "voltage_level": "medium voltage",
            "color": "rgb(31, 119, 180)",
            "active_power": 0.0,
            "reactive_power": 0.0,
            "id": 5
        },
        {
            "name": 6,
            "voltage_level": "medium voltage",
            "color": "rgb(31, 119, 180)",
            "active_power": 0.0,
            "reactive_power": 0.0,
            "id": 6
        },
        {
            "name": 7,
            "voltage_level": "medium voltage",
            "color": "rgb(31, 119, 180)",
            "active_power": 0.0,
            "reactive_power": 0.0,
            "id": 7
        },
        {
            "name": 8,
            "color": "rgb(255, 127, 14)",
            "voltage_level": "low voltage",
            "active_power": 0.898,
            "reactive_power": 0.898,
            "phase": "b",
            "id": 8
        },
        {
            "name": 9,
            "color": "rgb(255, 127, 14)",
            "voltage_level": "low voltage",
            "active_power": 0.738,
            "reactive_power": 0.738,
            "phase": "c",
            "id": 9
        },
        {
            "name": 10,
            "color": "rgb(255, 127, 14)",
            "voltage_level": "low voltage",
            "active_power": 0.999,
            "reactive_power": 0.999,
            "phase": "b",
            "id": 10
        },
        {
            "name": 11,
            "color": "rgb(255, 127, 14)",
            "voltage_level": "low voltage",
            "active_power": 1.085,
            "reactive_power": 1.085,
            "phase": "b",
            "id": 11
        },
        {
            "name": 12,
            "color": "rgb(255, 127, 14)",
            "voltage_level": "low voltage",
            "active_power": 1.177,
            "reactive_power": 1.177,
            "phase": "c",
            "id": 12
        },
        {
            "name": 13,
            "color": "rgb(255, 127, 14)",
            "voltage_level": "low voltage",
            "active_power": 1.282,
            "reactive_power": 1.282,
            "phase": "a",
            "id": 13
        },
        {
            "name": 14,
            "color": "rgb(255, 127, 14)",
            "voltage_level": "low voltage",
            "active_power": 0.914,
            "reactive_power": 0.914,
            "phase": "a",
            "id": 14
        },
        {
            "name": 15,
            "color": "rgb(255, 127, 14)",
            "voltage_level": "low voltage",
            "active_power": 0.84,
            "reactive_power": 0.84,
            "phase": "b",
            "id": 15
        },
        {
            "name": 16,
            "color": "rgb(255, 127, 14)",
            "voltage_level": "low voltage",
            "active_power": 1.125,
            "reactive_power": 1.125,
            "phase": "b",
            "id": 16
        },
        {
            "name": 17,
            "color": "rgb(255, 127, 14)",
            "voltage_level": "low voltage",
            "active_power": 1.232,
            "reactive_power": 1.232,
            "phase": "b",
            "id": 17
        },
        {
            "name": 18,
            "color": "rgb(255, 127, 14)",
            "voltage_level": "low voltage",
            "active_power": 0.986,
            "reactive_power": 0.986,
            "phase": "a",
            "id": 18
        },
        {
            "name": 19,
            "color": "rgb(255, 127, 14)",
            "voltage_level": "low voltage",
            "active_power": 0.993,
            "reactive_power": 0.993,
            "phase": "b",
            "id": 19
        },
        {
            "name": 20,
            "color": "rgb(255, 127, 14)",
            "voltage_level": "low voltage",
            "active_power": 0.875,
            "reactive_power": 0.875,
            "phase": "b",
            "id": 20
        },
        {
            "name": 21,
            "color": "rgb(255, 127, 14)",
            "voltage_level": "low voltage",
            "active_power": 1.087,
            "reactive_power": 1.087,
            "phase": "c",
            "id": 21
        },
        {
            "name": 22,
            "color": "rgb(255, 127, 14)",
            "voltage_level": "low voltage",
            "active_power": 1.207,
            "reactive_power": 1.207,
            "phase": "b",
            "id": 22
        },
        {
            "name": 23,
            "color": "rgb(255, 127, 14)",
            "voltage_level": "low voltage",
            "active_power": 1.164,
            "reactive_power": 1.164,
            "phase": "c",
            "id": 23
        },
        {
            "name": 24,
            "color": "rgb(255, 127, 14)",
            "voltage_level": "low voltage",
            "active_power": 1.117,
            "reactive_power": 1.117,
            "phase": "b",
            "id": 24
        },
        {
            "name": 25,
            "color": "rgb(255, 127, 14)",
            "voltage_level": "low voltage",
            "active_power": 0.888,
            "reactive_power": 0.888,
            "phase": "b",
            "id": 25
        },
        {
            "name": 26,
            "color": "rgb(255, 127, 14)",
            "voltage_level": "low voltage",
            "active_power": 0.942,
            "reactive_power": 0.942,
            "phase": "b",
            "id": 26
        },
        {
            "name": 27,
            "color": "rgb(255, 127, 14)",
            "voltage_level": "low voltage",
            "active_power": 1.007,
            "reactive_power": 1.007,
            "phase": "b",
            "id": 27
        },
        {
            "name": 28,
            "color": "rgb(255, 127, 14)",
            "voltage_level": "low voltage",
            "active_power": 0.721,
            "reactive_power": 0.721,
            "phase": "c",
            "id": 28
        },
        {
            "name": 29,
            "color": "rgb(255, 127, 14)",
            "voltage_level": "low voltage",
            "active_power": 1.165,
            "reactive_power": 1.165,
            "phase": "a",
            "id": 29
        },
        {
            "name": 30,
            "color": "rgb(255, 127, 14)",
            "voltage_level": "low voltage",
            "active_power": 0.893,
            "reactive_power": 0.893,
            "phase": "b",
            "id": 30
        },
        {
            "name": 31,
            "color": "rgb(255, 127, 14)",
            "voltage_level": "low voltage",
            "active_power": 1.26,
            "reactive_power": 1.26,
            "phase": "a",
            "id": 31
        },
        {
            "name": 32,
            "color": "rgb(255, 127, 14)",
            "voltage_level": "low voltage",
            "active_power": 0.861,
            "reactive_power": 0.861,
            "phase": "c",
            "id": 32
        },
        {
            "name": 33,
            "color": "rgb(255, 127, 14)",
            "voltage_level": "low voltage",
            "active_power": 1.079,
            "reactive_power": 1.079,
            "phase": "c",
            "id": 33
        },
        {
            "name": 34,
            "color": "rgb(255, 127, 14)",
            "voltage_level": "low voltage",
            "active_power": 1.298,
            "reactive_power": 1.298,
            "phase": "c",
            "id": 34
        },
        {
            "name": 35,
            "color": "rgb(255, 127, 14)",
            "voltage_level": "low voltage",
            "active_power": 0.853,
            "reactive_power": 0.853,
            "phase": "c",
            "id": 35
        },
        {
            "name": 36,
            "color": "rgb(255, 127, 14)",
            "voltage_level": "low voltage",
            "active_power": 0.828,
            "reactive_power": 0.828,
            "phase": "a",
            "id": 36
        },
        {
            "name": 37,
            "color": "rgb(255, 127, 14)",
            "voltage_level": "low voltage",
            "active_power": 1.227,
            "reactive_power": 1.227,
            "phase": "a",
            "id": 37
        },
        {
            "name": 38,
            "color": "rgb(255, 127, 14)",
            "voltage_level": "low voltage",
            "active_power": 1.02,
            "reactive_power": 1.02,
            "phase": "c",
            "id": 38
        },
        {
            "name": 39,
            "color": "rgb(255, 127, 14)",
            "voltage_level": "low voltage",
            "active_power": 1.245,
            "reactive_power": 1.245,
            "phase": "c",
            "id": 39
        },
        {
            "name": 40,
            "color": "rgb(255, 127, 14)",
            "voltage_level": "low voltage",
            "active_power": 0.697,
            "reactive_power": 0.697,
            "phase": "b",
            "id": 40
        },
        {
            "name": 41,
            "color": "rgb(255, 127, 14)",
            "voltage_level": "low voltage",
            "active_power": 1.217,
            "reactive_power": 1.217,
            "phase": "c",
            "id": 41
        },
        {
            "name": 42,
            "color": "rgb(255, 127, 14)",
            "voltage_level": "low voltage",
            "active_power": 0.788,
            "reactive_power": 0.788,
            "phase": "b",
            "id": 42
        },
        {
            "name": 43,
            "color": "rgb(255, 127, 14)",
            "voltage_level": "low voltage",
            "active_power": 0.805,
            "reactive_power": 0.805,
            "phase": "c",
            "id": 43
        },
        {
            "name": 44,
            "color": "rgb(255, 127, 14)",
            "voltage_level": "low voltage",
            "active_power": 1.07,
            "reactive_power": 1.07,
            "phase": "b",
            "id": 44
        },
        {
            "name": 45,
            "color": "rgb(255, 127, 14)",
            "voltage_level": "low voltage",
            "active_power": 1.018,
            "reactive_power": 1.018,
            "phase": "c",
            "id": 45
        },
        {
            "name": 46,
            "color": "rgb(255, 127, 14)",
            "voltage_level": "low voltage",
            "active_power": 0.845,
            "reactive_power": 0.845,
            "phase": "a",
            "id": 46
        },
        {
            "name": 47,
            "color": "rgb(255, 127, 14)",
            "voltage_level": "low voltage",
            "active_power": 0.907,
            "reactive_power": 0.907,
            "phase": "b",
            "id": 47
        },
        {
            "name": 48,
            "color": "rgb(255, 127, 14)",
            "voltage_level": "low voltage",
            "active_power": 1.251,
            "reactive_power": 1.251,
            "phase": "b",
            "id": 48
        },
        {
            "name": 49,
            "color": "rgb(255, 127, 14)",
            "voltage_level": "low voltage",
            "active_power": 0.764,
            "reactive_power": 0.764,
            "phase": "a",
            "id": 49
        },
        {
            "name": 50,
            "color": "rgb(255, 127, 14)",
            "voltage_level": "low voltage",
            "active_power": 0.995,
            "reactive_power": 0.995,
            "phase": "a",
            "id": 50
        },
        {
            "name": 51,
            "color": "rgb(255, 127, 14)",
            "voltage_level": "low voltage",
            "active_power": 1.275,
            "reactive_power": 1.275,
            "phase": "b",
            "id": 51
        },
        {
            "name": 52,
            "color": "rgb(255, 127, 14)",
            "voltage_level": "low voltage",
            "active_power": 1.166,
            "reactive_power": 1.166,
            "phase": "b",
            "id": 52
        },
        {
            "name": 53,
            "color": "rgb(255, 127, 14)",
            "voltage_level": "low voltage",
            "active_power": 0.932,
            "reactive_power": 0.932,
            "phase": "c",
            "id": 53
        },
        {
            "name": 54,
            "color": "rgb(255, 127, 14)",
            "voltage_level": "low voltage",
            "active_power": 0.877,
            "reactive_power": 0.877,
            "phase": "a",
            "id": 54
        },
        {
            "name": 55,
            "color": "rgb(255, 127, 14)",
            "voltage_level": "low voltage",
            "active_power": 0.786,
            "reactive_power": 0.786,
            "phase": "a",
            "id": 55
        },
        {
            "name": 56,
            "color": "rgb(255, 127, 14)",
            "voltage_level": "low voltage",
            "active_power": 1.027,
            "reactive_power": 1.027,
            "phase": "a",
            "id": 56
        },
        {
            "name": 57,
            "color": "rgb(255, 127, 14)",
            "voltage_level": "low voltage",
            "active_power": 0.962,
            "reactive_power": 0.962,
            "phase": "c",
            "id": 57
        },
        {
            "name": 58,
            "color": "rgb(255, 127, 14)",
            "voltage_level": "low voltage",
            "active_power": 0.905,
            "reactive_power": 0.905,
            "phase": "b",
            "id": 58
        },
        {
            "name": 59,
            "color": "rgb(255, 127, 14)",
            "voltage_level": "low voltage",
            "active_power": 1.018,
            "reactive_power": 1.018,
            "phase": "c",
            "id": 59
        },
        {
            "name": 60,
            "color": "rgb(255, 127, 14)",
            "voltage_level": "low voltage",
            "active_power": 0.71,
            "reactive_power": 0.71,
            "phase": "a",
            "id": 60
        },
        {
            "name": 61,
            "color": "rgb(255, 127, 14)",
            "voltage_level": "low voltage",
            "active_power": 0.806,
            "reactive_power": 0.806,
            "phase": "c",
            "id": 61
        },
        {
            "name": 62,
            "color": "rgb(255, 127, 14)",
            "voltage_level": "low voltage",
            "active_power": 1.161,
            "reactive_power": 1.161,
            "phase": "c",
            "id": 62
        },
        {
            "name": 63,
            "color": "rgb(255, 127, 14)",
            "voltage_level": "low voltage",
            "active_power": 0.703,
            "reactive_power": 0.703,
            "phase": "b",
            "id": 63
        },
        {
            "name": 64,
            "color": "rgb(255, 127, 14)",
            "voltage_level": "low voltage",
            "active_power": 1.242,
            "reactive_power": 1.242,
            "phase": "c",
            "id": 64
        },
        {
            "name": 65,
            "color": "rgb(255, 127, 14)",
            "voltage_level": "low voltage",
            "active_power": 1.243,
            "reactive_power": 1.243,
            "phase": "b",
            "id": 65
        },
        {
            "name": 66,
            "color": "rgb(255, 127, 14)",
            "voltage_level": "low voltage",
            "active_power": 1.005,
            "reactive_power": 1.005,
            "phase": "b",
            "id": 66
        },
        {
            "name": 67,
            "color": "rgb(255, 127, 14)",
            "voltage_level": "low voltage",
            "active_power": 1.001,
            "reactive_power": 1.001,
            "phase": "b",
            "id": 67
        },
        {
            "name": 68,
            "color": "rgb(255, 127, 14)",
            "voltage_level": "low voltage",
            "active_power": 1.11,
            "reactive_power": 1.11,
            "phase": "c",
            "id": 68
        },
        {
            "name": 69,
            "color": "rgb(255, 127, 14)",
            "voltage_level": "low voltage",
            "active_power": 1.104,
            "reactive_power": 1.104,
            "phase": "c",
            "id": 69
        },
        {
            "name": 70,
            "color": "rgb(255, 127, 14)",
            "voltage_level": "low voltage",
            "active_power": 0.964,
            "reactive_power": 0.964,
            "phase": "a",
            "id": 70
        },
        {
            "name": 71,
            "color": "rgb(255, 127, 14)",
            "voltage_level": "low voltage",
            "active_power": 0.881,
            "reactive_power": 0.881,
            "phase": "b",
            "id": 71
        },
        {
            "name": 72,
            "color": "rgb(255, 127, 14)",
            "voltage_level": "low voltage",
            "active_power": 0.813,
            "reactive_power": 0.813,
            "phase": "c",
            "id": 72
        },
        {
            "name": 73,
            "color": "rgb(255, 127, 14)",
            "voltage_level": "low voltage",
            "active_power": 0.877,
            "reactive_power": 0.877,
            "phase": "c",
            "id": 73
        },
        {
            "name": 74,
            "color": "rgb(255, 127, 14)",
            "voltage_level": "low voltage",
            "active_power": 0.791,
            "reactive_power": 0.791,
            "phase": "c",
            "id": 74
        },
        {
            "name": 75,
            "color": "rgb(255, 127, 14)",
            "voltage_level": "low voltage",
            "active_power": 0.811,
            "reactive_power": 0.811,
            "phase": "a",
            "id": 75
        },
        {
            "name": 76,
            "color": "rgb(255, 127, 14)",
            "voltage_level": "low voltage",
            "active_power": 1.164,
            "reactive_power": 1.164,
            "phase": "a",
            "id": 76
        },
        {
            "name": 77,
            "color": "rgb(255, 127, 14)",
            "voltage_level": "low voltage",
            "active_power": 1.181,
            "reactive_power": 1.181,
            "phase": "b",
            "id": 77
        },
        {
            "name": 78,
            "color": "rgb(255, 127, 14)",
            "voltage_level": "low voltage",
            "active_power": 0.975,
            "reactive_power": 0.975,
            "phase": "b",
            "id": 78
        },
        {
            "name": 79,
            "color": "rgb(255, 127, 14)",
            "voltage_level": "low voltage",
            "active_power": 0.971,
            "reactive_power": 0.971,
            "phase": "c",
            "id": 79
        }
    ],
    "links": [
        {
            "name": "Section_0_1",
            "type": "line",
            "length": 0.092,
            "switch": "sw_1",
            "source": 0,
            "target": 1
        },
        {
            "name": "Section_1_2",
            "type": "line",
            "length": 0.06,
            "switch": null,
            "source": 1,
            "target": 2
        },
        {
            "name": "Section_2_3",
            "type": "line",
            "length": 0.082,
            "switch": null,
            "source": 2,
            "target": 3
        },
        {
            "name": "Section_2_4",
            "type": "line",
            "length": 0.077,
            "switch": null,
            "source": 2,
            "target": 4
        },
        {
            "name": "Section_2_8",
            "type": "transformer",
            "switch": null,
            "source": 2,
            "target": 8
        },
        {
            "name": "Section_3_28",
            "type": "transformer",
            "switch": null,
            "source": 3,
            "target": 28
        },
        {
            "name": "Section_4_5",
            "type": "line",
            "length": 0.08,
            "switch": null,
            "source": 4,
            "target": 5
        },
        {
            "name": "Section_4_36",
            "type": "transformer",
            "switch": null,
            "source": 4,
            "target": 36
        },
        {
            "name": "Section_5_6",
            "type": "line",
            "length": 0.081,
            "switch": null,
            "source": 5,
            "target": 6
        },
        {
            "name": "Section_5_44",
            "type": "transformer",
            "switch": null,
            "source": 5,
            "target": 44
        },
        {
            "name": "Section_6_7",
            "type": "line",
            "length": 0.077,
            "switch": null,
            "source": 6,
            "target": 7
        },
        {
            "name": "Section_6_64",
            "type": "transformer",
            "switch": null,
            "source": 6,
            "target": 64
        },
        {
            "name": "Section_7_72",
            "type": "transformer",
            "switch": null,
            "source": 7,
            "target": 72
        },
        {
            "name": "Section_8_9",
            "type": "line",
            "length": 0.009,
            "switch": null,
            "source": 8,
            "target": 9
        },
        {
            "name": "Section_9_10",
            "type": "line",
            "length": 0.007,
            "switch": null,
            "source": 9,
            "target": 10
        },
        {
            "name": "Section_10_11",
            "type": "line",
            "length": 0.007,
            "switch": null,
            "source": 10,
            "target": 11
        },
        {
            "name": "Section_11_12",
            "type": "line",
            "length": 0.009,
            "switch": null,
            "source": 11,
            "target": 12
        },
        {
            "name": "Section_12_13",
            "type": "line",
            "length": 0.008,
            "switch": null,
            "source": 12,
            "target": 13
        },
        {
            "name": "Section_13_14",
            "type": "line",
            "length": 0.007,
            "switch": null,
            "source": 13,
            "target": 14
        },
        {
            "name": "Section_13_15",
            "type": "line",
            "length": 0.008,
            "switch": null,
            "source": 13,
            "target": 15
        },
        {
            "name": "Section_13_16",
            "type": "line",
            "length": 0.007,
            "switch": null,
            "source": 13,
            "target": 16
        },
        {
            "name": "Section_16_17",
            "type": "line",
            "length": 0.009,
            "switch": null,
            "source": 16,
            "target": 17
        },
        {
            "name": "Section_16_19",
            "type": "line",
            "length": 0.006,
            "switch": null,
            "source": 16,
            "target": 19
        },
        {
            "name": "Section_16_21",
            "type": "line",
            "length": 0.01,
            "switch": null,
            "source": 16,
            "target": 21
        },
        {
            "name": "Section_17_18",
            "type": "line",
            "length": 0.007,
            "switch": null,
            "source": 17,
            "target": 18
        },
        {
            "name": "Section_19_20",
            "type": "line",
            "length": 0.01,
            "switch": null,
            "source": 19,
            "target": 20
        },
        {
            "name": "Section_21_22",
            "type": "line",
            "length": 0.009,
            "switch": null,
            "source": 21,
            "target": 22
        },
        {
            "name": "Section_22_23",
            "type": "line",
            "length": 0.008,
            "switch": null,
            "source": 22,
            "target": 23
        },
        {
            "name": "Section_23_24",
            "type": "line",
            "length": 0.006,
            "switch": null,
            "source": 23,
            "target": 24
        },
        {
            "name": "Section_23_26",
            "type": "line",
            "length": 0.009,
            "switch": null,
            "source": 23,
            "target": 26
        },
        {
            "name": "Section_24_25",
            "type": "line",
            "length": 0.006,
            "switch": null,
            "source": 24,
            "target": 25
        },
        {
            "name": "Section_26_27",
            "type": "line",
            "length": 0.01,
            "switch": null,
            "source": 26,
            "target": 27
        },
        {
            "name": "Section_28_29",
            "type": "line",
            "length": 0.009,
            "switch": null,
            "source": 28,
            "target": 29
        },
        {
            "name": "Section_28_30",
            "type": "line",
            "length": 0.006,
            "switch": null,
            "source": 28,
            "target": 30
        },
        {
            "name": "Section_30_31",
            "type": "line",
            "length": 0.009,
            "switch": null,
            "source": 30,
            "target": 31
        },
        {
            "name": "Section_31_32",
            "type": "line",
            "length": 0.008,
            "switch": null,
            "source": 31,
            "target": 32
        },
        {
            "name": "Section_32_33",
            "type": "line",
            "length": 0.01,
            "switch": null,
            "source": 32,
            "target": 33
        },
        {
            "name": "Section_32_34",
            "type": "line",
            "length": 0.007,
            "switch": null,
            "source": 32,
            "target": 34
        },
        {
            "name": "Section_34_35",
            "type": "line",
            "length": 0.008,
            "switch": null,
            "source": 34,
            "target": 35
        },
        {
            "name": "Section_36_37",
            "type": "line",
            "length": 0.006,
            "switch": null,
            "source": 36,
            "target": 37
        },
        {
            "name": "Section_37_38",
            "type": "line",
            "length": 0.007,
            "switch": null,
            "source": 37,
            "target": 38
        },
        {
            "name": "Section_38_39",
            "type": "line",
            "length": 0.008,
            "switch": null,
            "source": 38,
            "target": 39
        },
        {
            "name": "Section_38_41",
            "type": "line",
            "length": 0.01,
            "switch": null,
            "source": 38,
            "target": 41
        },
        {
            "name": "Section_38_42",
            "type": "line",
            "length": 0.009,
            "switch": null,
            "source": 38,
            "target": 42
        },
        {
            "name": "Section_39_40",
            "type": "line",
            "length": 0.007,
            "switch": null,
            "source": 39,
            "target": 40
        },
        {
            "name": "Section_42_43",
            "type": "line",
            "length": 0.008,
            "switch": null,
            "source": 42,
            "target": 43
        },
        {
            "name": "Section_44_45",
            "type": "line",
            "length": 0.008,
            "switch": null,
            "source": 44,
            "target": 45
        },
        {
            "name": "Section_45_46",
            "type": "line",
            "length": 0.008,
            "switch": null,
            "source": 45,
            "target": 46
        },
        {
            "name": "Section_45_48",
            "type": "line",
            "length": 0.007,
            "switch": null,
            "source": 45,
            "target": 48
        },
        {
            "name": "Section_45_49",
            "type": "line",
            "length": 0.01,
            "switch": null,
            "source": 45,
            "target": 49
        },
        {
            "name": "Section_46_47",
            "type": "line",
            "length": 0.008,
            "switch": null,
            "source": 46,
            "target": 47
        },
        {
            "name": "Section_48_50",
            "type": "line",
            "length": 0.007,
            "switch": null,
            "source": 48,
            "target": 50
        },
        {
            "name": "Section_48_55",
            "type": "line",
            "length": 0.009,
            "switch": null,
            "source": 48,
            "target": 55
        },
        {
            "name": "Section_48_57",
            "type": "line",
            "length": 0.008,
            "switch": null,
            "source": 48,
            "target": 57
        },
        {
            "name": "Section_50_51",
            "type": "line",
            "length": 0.007,
            "switch": null,
            "source": 50,
            "target": 51
        },
        {
            "name": "Section_50_52",
            "type": "line",
            "length": 0.009,
            "switch": null,
            "source": 50,
            "target": 52
        },
        {
            "name": "Section_50_53",
            "type": "line",
            "length": 0.009,
            "switch": null,
            "source": 50,
            "target": 53
        },
        {
            "name": "Section_53_54",
            "type": "line",
            "length": 0.009,
            "switch": null,
            "source": 53,
            "target": 54
        },
        {
            "name": "Section_55_56",
            "type": "line",
            "length": 0.008,
            "switch": null,
            "source": 55,
            "target": 56
        },
        {
            "name": "Section_57_58",
            "type": "line",
            "length": 0.008,
            "switch": null,
            "source": 57,
            "target": 58
        },
        {
            "name": "Section_58_59",
            "type": "line",
            "length": 0.007,
            "switch": null,
            "source": 58,
            "target": 59
        },
        {
            "name": "Section_58_60",
            "type": "line",
            "length": 0.009,
            "switch": null,
            "source": 58,
            "target": 60
        },
        {
            "name": "Section_60_61",
            "type": "line",
            "length": 0.007,
            "switch": null,
            "source": 60,
            "target": 61
        },
        {
            "name": "Section_61_62",
            "type": "line",
            "length": 0.01,
            "switch": null,
            "source": 61,
            "target": 62
        },
        {
            "name": "Section_62_63",
            "type": "line",
            "length": 0.009,
            "switch": null,
            "source": 62,
            "target": 63
        },
        {
            "name": "Section_64_65",
            "type": "line",
            "length": 0.009,
            "switch": null,
            "source": 64,
            "target": 65
        },
        {
            "name": "Section_65_66",
            "type": "line",
            "length": 0.01,
            "switch": null,
            "source": 65,
            "target": 66
        },
        {
            "name": "Section_65_67",
            "type": "line",
            "length": 0.008,
            "switch": null,
            "source": 65,
            "target": 67
        },
        {
            "name": "Section_67_68",
            "type": "line",
            "length": 0.007,
            "switch": null,
            "source": 67,
            "target": 68
        },
        {
            "name": "Section_67_70",
            "type": "line",
            "length": 0.008,
            "switch": null,
            "source": 67,
            "target": 70
        },
        {
            "name": "Section_68_69",
            "type": "line",
            "length": 0.007,
            "switch": null,
            "source": 68,
            "target": 69
        },
        {
            "name": "Section_70_71",
            "type": "line",
            "length": 0.009,
            "switch": null,
            "source": 70,
            "target": 71
        },
        {
            "name": "Section_72_73",
            "type": "line",
            "length": 0.007,
            "switch": null,
            "source": 72,
            "target": 73
        },
        {
            "name": "Section_72_74",
            "type": "line",
            "length": 0.007,
            "switch": null,
            "source": 72,
            "target": 74
        },
        {
            "name": "Section_74_75",
            "type": "line",
            "length": 0.007,
            "switch": null,
            "source": 74,
            "target": 75
        },
        {
            "name": "Section_75_76",
            "type": "line",
            "length": 0.009,
            "switch": null,
            "source": 75,
            "target": 76
        },
        {
            "name": "Section_76_77",
            "type": "line",
            "length": 0.01,
            "switch": null,
            "source": 76,
            "target": 77
        },
        {
            "name": "Section_77_78",
            "type": "line",
            "length": 0.007,
            "switch": null,
            "source": 77,
            "target": 78
        },
        {
            "name": "Section_77_79",
            "type": "line",
            "length": 0.009,
            "switch": null,
            "source": 77,
            "target": 79
        }
    ],
    "transformes": [
        {
            "name": "trafo_2_8",
            "source": 2,
            "target": 8,
            "power": 45.0
        },
        {
            "name": "trafo_3_28",
            "source": 3,
            "target": 28,
            "power": 112.5
        },
        {
            "name": "trafo_4_36",
            "source": 4,
            "target": 36,
            "power": 112.5
        },
        {
            "name": "trafo_5_44",
            "source": 5,
            "target": 44,
            "power": 15.0
        },
        {
            "name": "trafo_6_64",
            "source": 6,
            "target": 64,
            "power": 45.0
        },
        {
            "name": "trafo_7_72",
            "source": 7,
            "target": 72,
            "power": 45.0
        }
    ]
}